LogVictoriaLogs/__init__.py
logvictorialogs-0.1.6.dist-info/licenses/LICENSE
logvictorialogs-0.1.6.dist-info/METADATA
logvictorialogs-0.1.6.dist-info/WHEEL
logvictorialogs-0.1.6.dist-info/top_level.txt
logvictorialogs-0.1.6.dist-info/RECORD
