Metadata-Version: 2.4
Name: LogVictoriaLogs
Version: 0.1.6
Summary: Python client for VictoriaLogs integration
Home-page: https://github.com/yourusername/LogVictoriaLogs
Author: Author
Author-email: Author <author@example.com>
License: MIT License
Project-URL: Homepage, https://github.com/yourusername/LogVictoriaLogs
Project-URL: Bug Tracker, https://github.com/yourusername/LogVictoriaLogs/issues
Classifier: Programming Language :: Python :: 3
Classifier: License :: OSI Approved :: MIT License
Classifier: Operating System :: OS Independent
Requires-Python: >=3.7
License-File: LICENSE
Dynamic: author
Dynamic: home-page
Dynamic: license-file
Dynamic: requires-python
